check_code-0.1.4.dist-info/METADATA
check_code-0.1.4.dist-info/WHEEL
check_code-0.1.4.dist-info/entry_points.txt
check_code/.flake8
check_code/__init__.py
check_code/check.py
check_code-0.1.4.dist-info/RECORD
